mcp_redmine/__init__.py
mcp_redmine/filter_presets.py
mcp_redmine/journal_filters.py
mcp_redmine/mcp_capabilities.py
mcp_redmine/redmine_openapi.yml
mcp_redmine/response_filters.py
mcp_redmine/server.py
mcp_redmine_enhanced-2025.9.13.162715.post0.dist-info/METADATA
mcp_redmine_enhanced-2025.9.13.162715.post0.dist-info/WHEEL
mcp_redmine_enhanced-2025.9.13.162715.post0.dist-info/entry_points.txt
mcp_redmine_enhanced-2025.9.13.162715.post0.dist-info/licenses/LICENSE
mcp_redmine_enhanced-2025.9.13.162715.post0.dist-info/RECORD
