Metadata-Version: 2.4
Name: mcp-redmine-enhanced
Version: 2025.9.13.162715.post0
Summary: A MCP server that connects to your Redmine instance (Active Fork)
Project-URL: Homepage, https://github.com/olssonsten/mcp-redmine
Project-URL: Issues, https://github.com/olssonsten/mcp-redmine/issues
Project-URL: Discussions, https://github.com/olssonsten/mcp-redmine/discussions
Project-URL: Original Repository, https://github.com/runekaagaard/mcp-redmine
Author: Rune Kaagaard
Author-email: Sten Olsson <155102857+olssonsten@users.noreply.github.com>
License-File: LICENSE
Classifier: Operating System :: OS Independent
Classifier: Programming Language :: Python :: 3
Requires-Python: >=3.10
Requires-Dist: httpx>=0.28.1
Requires-Dist: mcp[cli]>=1.3.0
Requires-Dist: openapi-core>=0.19.4
Requires-Dist: pyyaml>=6.0.2
